okx_dex_mcp/__init__.py
okx_dex_mcp/main.py
okx_dex_mcp/analysis/__init__.py
okx_dex_mcp/analysis/account.py
okx_dex_mcp/analysis/dex_analysis.py
okx_dex_mcp/analysis/kol_analysis.py
okx_dex_mcp/analysis/market_data.py
okx_dex_mcp/analysis/twitter_intelligence.py
okx_dex_mcp/api/__init__.py
okx_dex_mcp/api/mesh_api.py
okx_dex_mcp/api/okx_api.py
okx_dex_mcp/swap/__init__.py
okx_dex_mcp/swap/quotes.py
okx_dex_mcp/swap/swaps.py
okx_dex_mcp/utils/__init__.py
okx_dex_mcp/utils/blockchain.py
okx_dex_mcp/utils/constants.py
okx_dex_mcp/utils/formatters.py
okx_dex_mcp-0.1.8.dist-info/METADATA
okx_dex_mcp-0.1.8.dist-info/WHEEL
okx_dex_mcp-0.1.8.dist-info/entry_points.txt
okx_dex_mcp-0.1.8.dist-info/licenses/LICENSE
okx_dex_mcp-0.1.8.dist-info/RECORD
