Metadata-Version: 2.4
Name: okx-dex-mcp
Version: 0.1.8
Summary: OKX DEX Trading MCP Server - Model Context Protocol server for decentralized exchange trading via OKX API
Project-URL: Homepage, https://github.com/okx/okx-dex-mcp
Project-URL: Documentation, https://github.com/okx/okx-dex-mcp#readme
Project-URL: Repository, https://github.com/okx/okx-dex-mcp.git
Project-URL: Issues, https://github.com/okx/okx-dex-mcp/issues
Project-URL: Changelog, https://github.com/okx/okx-dex-mcp/blob/main/CHANGELOG.md
Author-email: OKX DEX MCP Team <support@example.com>
Maintainer-email: OKX DEX MCP Team <support@example.com>
License: MIT
License-File: LICENSE
Keywords: blockchain,bsc,cross-chain,cryptocurrency,defi,dex,ethereum,mcp,model-context-protocol,okx,polygon,swap,trading,web3
Classifier: Development Status :: 4 - Beta
Classifier: Intended Audience :: Developers
Classifier: Intended Audience :: Financial and Insurance Industry
Classifier: License :: OSI Approved :: MIT License
Classifier: Operating System :: OS Independent
Classifier: Programming Language :: Python :: 3
Classifier: Programming Language :: Python :: 3.9
Classifier: Programming Language :: Python :: 3.10
Classifier: Programming Language :: Python :: 3.11
Classifier: Programming Language :: Python :: 3.12
Classifier: Programming Language :: Python :: 3.13
Classifier: Topic :: Internet :: WWW/HTTP :: Dynamic Content
Classifier: Topic :: Office/Business :: Financial
Classifier: Topic :: Scientific/Engineering :: Information Analysis
Classifier: Topic :: Software Development :: Libraries :: Python Modules
Requires-Python: >=3.10
Requires-Dist: eth-account>=0.10.0
Requires-Dist: fastmcp>=2.5.1
Requires-Dist: httpx>=0.28.1
Requires-Dist: mcp>=1.9.1
Requires-Dist: python-dotenv>=1.1.0
Requires-Dist: solders>=0.21.0
Requires-Dist: web3>=6.15.0
Provides-Extra: dev
Requires-Dist: black>=23.0.0; extra == 'dev'
Requires-Dist: flake8>=6.0.0; extra == 'dev'
Requires-Dist: isort>=5.12.0; extra == 'dev'
Requires-Dist: mypy>=1.0.0; extra == 'dev'
Requires-Dist: pre-commit>=3.0.0; extra == 'dev'
Requires-Dist: pytest-asyncio>=0.21.0; extra == 'dev'
Requires-Dist: pytest>=7.0.0; extra == 'dev'
Provides-Extra: test
Requires-Dist: httpx[test]>=0.28.1; extra == 'test'
Requires-Dist: pytest-asyncio>=0.21.0; extra == 'test'
Requires-Dist: pytest-cov>=4.0.0; extra == 'test'
Requires-Dist: pytest>=7.0.0; extra == 'test'
